finbourne_lab/__init__.py
finbourne_lab/analysis/__init__.py
finbourne_lab/analysis/ab_test.py
finbourne_lab/analysis/distribution.py
finbourne_lab/analysis/linear.py
finbourne_lab/analysis/plotting.py
finbourne_lab/common/__init__.py
finbourne_lab/common/base_lab.py
finbourne_lab/common/convener.py
finbourne_lab/common/ensure.py
finbourne_lab/common/experiment.py
finbourne_lab/common/observation.py
finbourne_lab/common/sdk_experiment.py
finbourne_lab/common/shopper.py
finbourne_lab/common/recorder/__init__.py
finbourne_lab/common/recorder/base.py
finbourne_lab/common/recorder/drive.py
finbourne_lab/common/recorder/file.py
finbourne_lab/common/recorder/no_op.py
finbourne_lab/common/recorder/sql_db.py
finbourne_lab/luminesce/__init__.py
finbourne_lab/luminesce/__main__.py
finbourne_lab/luminesce/base.py
finbourne_lab/luminesce/core.py
finbourne_lab/luminesce/drive.py
finbourne_lab/luminesce/ensure.py
finbourne_lab/luminesce/experiment.py
finbourne_lab/luminesce/shopper_setup.py
finbourne_lab/luminesce/utils.py
finbourne_lab/luminesce/lusid/__init__.py
finbourne_lab/luminesce/lusid/base.py
finbourne_lab/luminesce/lusid/lusid_read.py
finbourne_lab/luminesce/lusid/lusid_write.py
finbourne_lab/lusid/__init__.py
finbourne_lab/lusid/base.py
finbourne_lab/lusid/client.py
finbourne_lab/lusid/ensure.py
finbourne_lab/lusid/experiment.py
finbourne_lab/lusid/holding.py
finbourne_lab/lusid/instrument.py
finbourne_lab/lusid/quote.py
finbourne_lab/lusid/transaction.py
finbourne_lab_test/__init__.py
finbourne_lab_test/integration/__init__.py
finbourne_lab_test/integration/luminesce/__init__.py
finbourne_lab_test/integration/lusid/__init__.py
finbourne_lab_test/unit/__init__.py
finbourne_lab_test/unit/analysis/__init__.py
finbourne_lab_test/unit/analysis/test_ab_test.py
finbourne_lab_test/unit/analysis/test_distribution.py
finbourne_lab_test/unit/analysis/test_linear.py
finbourne_lab_test/unit/common/__init__.py
finbourne_lab_test/unit/common/test_convener.py
fbnlab_preview-0.1.109.dist-info/METADATA
fbnlab_preview-0.1.109.dist-info/WHEEL
fbnlab_preview-0.1.109.dist-info/top_level.txt
fbnlab_preview-0.1.109.dist-info/RECORD
