Metadata-Version: 2.1
Name: fbnlab-preview
Version: 0.1.109
Summary: Python library for performance measurement of Finbourne apps
Home-page: UNKNOWN
Author: FINBOURNE Technology
Author-email: engineering@finbourne.com
License: UNKNOWN
Platform: UNKNOWN
Classifier: Programming Language :: Python :: 3
Classifier: Operating System :: OS Independent
Requires-Python: >=3.8
Requires-Dist: pandas (>=2.0.0)
Requires-Dist: numpy
Requires-Dist: tqdm
Requires-Dist: matplotlib
Requires-Dist: statsmodels
Requires-Dist: scipy
Requires-Dist: dve-lumipy-preview
Requires-Dist: lusid-sdk-preview
Requires-Dist: shortuuid
